gmssl/__init__.py
gmssl/func.py
gmssl/sm2.py
gmssl/sm3.py
gmssl/sm4.py
gmssl_tools-2.7.8.dist-info/DESCRIPTION.rst
gmssl_tools-2.7.8.dist-info/METADATA
gmssl_tools-2.7.8.dist-info/RECORD
gmssl_tools-2.7.8.dist-info/WHEEL
gmssl_tools-2.7.8.dist-info/metadata.json
gmssl_tools-2.7.8.dist-info/top_level.txt
