Metadata-Version: 2.0
Name: gmssl-tools
Version: 2.7.8
Summary: Pure-Python SM2/SM3/SM4 implementation
Home-page: https://github.com/knitmesh/gmssl
Author: jingh
Author-email: jingh.lib@gmail.com
License: BSD
Platform: all platform
